tinydbstorage/__init__.py
tinydbstorage/schema/__init__.py
tinydbstorage/schema/s3_schema.py
tinydbstorage/storage/__init__.py
tinydbstorage/storage/file.py
tinydbstorage/storage/memory.py
tinydbstorage/storage/redis.py
tinydbstorage/storage/s3.py
tinydb_storage-0.1.0.dist-info/LICENSE
tinydb_storage-0.1.0.dist-info/METADATA
tinydb_storage-0.1.0.dist-info/WHEEL
tinydb_storage-0.1.0.dist-info/top_level.txt
tinydb_storage-0.1.0.dist-info/RECORD
