Metadata-Version: 2.1
Name: tinydb-storage
Version: 0.1.0
Summary: Wrapper tinydb storage
Home-page: https://mnc-repo.mncdigital.com/ai-team/vision_plus/rce_offline_results_module
Author: Ferdina Kusumah
Author-email: ferdina.kusumah@gmail.com
License: MIT
Platform: UNKNOWN
Classifier: License :: OSI Approved :: MIT License
Classifier: Programming Language :: Python :: 3
Classifier: Programming Language :: Python :: 3.7
Classifier: Programming Language :: Python :: 3.8
Classifier: Programming Language :: Python :: 3.9
Classifier: Programming Language :: Python :: 3.10
License-File: LICENSE
Requires-Dist: tinydb (>=4.5.0)
Requires-Dist: redis (>=4.0.0)
Requires-Dist: pydantic (>=1.5)
Requires-Dist: cachetools (>=4.2.0)
Requires-Dist: boto3 (>=1.24.18)
